MANIFEST.in
README.rst
setup.py
zim_places/__init__.py
zim_places/cities.py
zim_places/districts.py
zim_places/provinces.py
zim_places/wards.py
zim_places.egg-info/PKG-INFO
zim_places.egg-info/SOURCES.txt
zim_places.egg-info/dependency_links.txt
zim_places.egg-info/requires.txt
zim_places.egg-info/top_level.txt
zim_places/components/cities.csv
zim_places/components/districts.csv
zim_places/components/provinces.csv
zim_places/components/wards.csv