Metadata-Version: 1.1
Name: zim-places
Version: 1.1.3
Summary: A package for wards,districts,cities and provinces in Zimbabwe
Home-page: https://github.com/RONALD55/ZimPlaces-Python-Library
Author: Ronald Nyasha Kanyepi
Author-email: kanyepironald@gmail.com
License: MIT
Keywords: zimbabwe,cities in Zimbabwe,districts in Zimbabwe,wards in Zimbabwe,Provinces in Zimbabwe,Zimbabwe zim_places
Platform: UNKNOWN
Classifier: Development Status :: 5 - Production/Stable
Classifier: Intended Audience :: Education
Classifier: Intended Audience :: Developers
Classifier: Operating System :: Microsoft :: Windows :: Windows 10
Classifier: License :: OSI Approved :: MIT License
Classifier: Programming Language :: Python :: 3
